ludwig/__init__.py
ludwig/api.py
ludwig/cli.py
ludwig/collect.py
ludwig/constants.py
ludwig/contrib.py
ludwig/experiment.py
ludwig/globals.py
ludwig/predict.py
ludwig/serve.py
ludwig/test_performance.py
ludwig/train.py
ludwig/visualize.py
ludwig/contribs/__init__.py
ludwig/contribs/comet.py
ludwig/data/__init__.py
ludwig/data/concatenate_datasets.py
ludwig/data/dataset.py
ludwig/data/dataset_synthesyzer.py
ludwig/data/postprocessing.py
ludwig/data/preprocessing.py
ludwig/data/split_dataset.py
ludwig/features/__init__.py
ludwig/features/audio_feature.py
ludwig/features/bag_feature.py
ludwig/features/base_feature.py
ludwig/features/binary_feature.py
ludwig/features/category_feature.py
ludwig/features/date_feature.py
ludwig/features/feature_registries.py
ludwig/features/feature_utils.py
ludwig/features/h3_feature.py
ludwig/features/image_feature.py
ludwig/features/numerical_feature.py
ludwig/features/sequence_feature.py
ludwig/features/set_feature.py
ludwig/features/text_feature.py
ludwig/features/timeseries_feature.py
ludwig/features/vector_feature.py
ludwig/models/__init__.py
ludwig/models/combiners.py
ludwig/models/inputs.py
ludwig/models/model.py
ludwig/models/outputs.py
ludwig/models/modules/__init__.py
ludwig/models/modules/attention_modules.py
ludwig/models/modules/convolutional_modules.py
ludwig/models/modules/date_encoders.py
ludwig/models/modules/dense_encoders.py
ludwig/models/modules/embedding_modules.py
ludwig/models/modules/fully_connected_modules.py
ludwig/models/modules/h3_encoders.py
ludwig/models/modules/image_encoders.py
ludwig/models/modules/initializer_modules.py
ludwig/models/modules/loss_modules.py
ludwig/models/modules/measure_modules.py
ludwig/models/modules/optimization_modules.py
ludwig/models/modules/recurrent_modules.py
ludwig/models/modules/reduction_modules.py
ludwig/models/modules/sequence_decoders.py
ludwig/models/modules/sequence_encoders.py
ludwig/utils/__init__.py
ludwig/utils/algorithms_utils.py
ludwig/utils/audio_utils.py
ludwig_myelin-0.2.1.37.dist-info/LICENSE
ludwig_myelin-0.2.1.37.dist-info/METADATA
ludwig_myelin-0.2.1.37.dist-info/WHEEL
ludwig_myelin-0.2.1.37.dist-info/entry_points.txt
ludwig_myelin-0.2.1.37.dist-info/top_level.txt
ludwig_myelin-0.2.1.37.dist-info/RECORD
