Metadata-Version: 2.1
Name: ludwig-myelin
Version: 0.2.1.37
Summary: A deep learning experimentation toolbox
Home-page: https://ludwig.ai
Author: Piero Molino
Author-email: piero.molino@gmail.com
License: Apache 2.0
Keywords: ludwig deep learning deep_learning machine machine_learning natural language processing computer vision
Platform: UNKNOWN
Requires-Python: >=3
Requires-Dist: Cython (>=0.25)
Requires-Dist: h5py (>=2.6)
Requires-Dist: numpy (>=1.15)
Requires-Dist: pandas (>=0.19)
Requires-Dist: scipy (>=0.18)
Requires-Dist: tabulate (>=0.7)
Requires-Dist: scikit-learn
Requires-Dist: tqdm
Requires-Dist: tensorflow (==1.15.0)
Requires-Dist: PyYAML (>=3.12)
Requires-Dist: absl-py
Requires-Dist: myelin (>=0.0.37)
Requires-Dist: Jinja2 (>=2.10.3)
Provides-Extra: audio
Requires-Dist: soundfile ; extra == 'audio'
Provides-Extra: full
Requires-Dist: matplotlib (>=3.0) ; extra == 'full'
Requires-Dist: seaborn (>=0.7) ; extra == 'full'
Requires-Dist: spacy (>=2.2) ; extra == 'full'
Requires-Dist: bert-tensorflow ; extra == 'full'
Requires-Dist: scikit-image (==0.14.2) ; extra == 'full'
Requires-Dist: soundfile ; extra == 'full'
Requires-Dist: uvicorn ; extra == 'full'
Requires-Dist: fastapi ; extra == 'full'
Requires-Dist: pydantic (==0.32.2) ; extra == 'full'
Requires-Dist: python-multipart ; extra == 'full'
Provides-Extra: gpu
Requires-Dist: tensorflow-gpu (==1.15.0) ; extra == 'gpu'
Provides-Extra: image
Requires-Dist: scikit-image (==0.14.2) ; extra == 'image'
Provides-Extra: serve
Requires-Dist: uvicorn ; extra == 'serve'
Requires-Dist: fastapi ; extra == 'serve'
Requires-Dist: pydantic (==0.32.2) ; extra == 'serve'
Requires-Dist: python-multipart ; extra == 'serve'
Provides-Extra: test
Requires-Dist: matplotlib (>=3.0) ; extra == 'test'
Requires-Dist: seaborn (>=0.7) ; extra == 'test'
Requires-Dist: spacy (>=2.2) ; extra == 'test'
Requires-Dist: bert-tensorflow ; extra == 'test'
Requires-Dist: scikit-image (==0.14.2) ; extra == 'test'
Requires-Dist: soundfile ; extra == 'test'
Requires-Dist: uvicorn ; extra == 'test'
Requires-Dist: fastapi ; extra == 'test'
Requires-Dist: pydantic (==0.32.2) ; extra == 'test'
Requires-Dist: python-multipart ; extra == 'test'
Requires-Dist: pytest ; extra == 'test'
Provides-Extra: text
Requires-Dist: spacy (>=2.2) ; extra == 'text'
Requires-Dist: bert-tensorflow ; extra == 'text'
Provides-Extra: viz
Requires-Dist: matplotlib (>=3.0) ; extra == 'viz'
Requires-Dist: seaborn (>=0.7) ; extra == 'viz'
